diss/__init__.py
diss/annotated_mc.py
diss/concept_classes/__init__.py
diss/concept_classes/dfa_concept.py
diss/domains/__init__.py
diss/domains/gridworld_circ.py
diss/domains/gridworld_naive.py
diss/experiment/__init__.py
diss/experiment/analyze.py
diss/experiment/concept_class.py
diss/experiment/planner.py
diss/experiment/utils.py
diss/experiment/vis.py
diss/learn.py
diss/planners/__init__.py
diss/planners/product_mc.py
diss/planners/tabular.py
diss/prefix_tree.py
diss-0.2.12.dist-info/LICENSE
diss-0.2.12.dist-info/METADATA
diss-0.2.12.dist-info/WHEEL
diss-0.2.12.dist-info/RECORD
