Metadata-Version: 2.1
Name: diss
Version: 0.2.12
Summary: Demonstration Informed Specification Search
License: MIT
Author: Marcell Vazquez-Chanlatte
Author-email: mvc@linux.com
Requires-Python: >=3.9,<4.0
Classifier: License :: OSI Approved :: MIT License
Classifier: Programming Language :: Python :: 3
Classifier: Programming Language :: Python :: 3.9
Classifier: Programming Language :: Python :: 3.10
Classifier: Programming Language :: Python :: 3.11
Requires-Dist: attrs (>=22.0,<23.0)
Requires-Dist: funcy (>=1.16,<2.0)
Requires-Dist: jupyterlab (>=3.3.1,<4.0.0)
Requires-Dist: numpy (>=1.21.2,<2.0.0)
Requires-Dist: scipy (>=1.7.2,<2.0.0)
